fixtup/__init__.py
fixtup/exceptions.py
fixtup/factory.py
fixtup/fixtup.py
fixtup/logger.py
fixtup/os.py
fixtup/py.typed
fixtup/cli/__init__.py
fixtup/cli/base.py
fixtup/cli/commands/__init__.py
fixtup/cli/commands/info.py
fixtup/cli/commands/init.py
fixtup/cli/commands/new.py
fixtup/entity/__init__.py
fixtup/entity/fixtup_process.py
fixtup/entity/fixture.py
fixtup/entity/fixture_template.py
fixtup/entity/plugin.py
fixtup/entity/project_manifest.py
fixtup/entity/settings.py
fixtup/fixture/__init__.py
fixtup/fixture/base.py
fixtup/fixture/factory.py
fixtup/fixture_template/__init__.py
fixtup/fixture_template/base.py
fixtup/helper/__init__.py
fixtup/helper/base.py
fixtup/hook/__init__.py
fixtup/hook/base.py
fixtup/hook/factory.py
fixtup/hook/mock.py
fixtup/hook/python.py
fixtup/lib/__init__.py
fixtup/lib/conditions.py
fixtup/lib/enum.py
fixtup/lib/env.py
fixtup/lib/list.py
fixtup/lib/signal.py
fixtup/plugin/__init__.py
fixtup/plugin/base.py
fixtup/plugin/factory.py
fixtup/plugin/mock.py
fixtup/plugin/python.py
fixtup/plugins/__init__.py
fixtup/plugins/docker.py
fixtup/plugins/dotenv.py
fixtup/plugins/dummy_plugin.py
fixtup/plugins/dummy_plugin_error.py
fixtup/plugins/resource/docker/docker-compose.yml
fixtup/plugins/resource/dotenv/.env
fixtup/prompt/__init__.py
fixtup/prompt/base.py
fixtup/prompt/factory.py
fixtup/prompt/mock.py
fixtup/prompt/prompt_toolkit.py
fixtup/scaffold/__init__.py
fixtup/scaffold/base.py
fixtup/scaffold/resource/fixtup.yml.j2
fixtup/scaffold/resource/hooks/hook_setup_data.py.sample
fixtup/scaffold/resource/hooks/hook_started.py.sample
fixtup/scaffold/resource/hooks/hook_stopping.py.sample
fixtup/scaffold/resource/hooks/hook_teardown_data.py.sample
fixtup/settings/__init__.py
fixtup/settings/base.py
fixtup/settings/factory.py
fixtup/settings/module.py
fixtup/settings/pyproject_toml.py
fixtup/settings/setup_cfg.py
fixtup/settings/resource/pyproject_toml_settings.in
fixtup/settings/resource/setup_cfg_settings.in
fixtup/tests/__init__.py
fixtup-0.1.5.dist-info/LICENSE.md
fixtup-0.1.5.dist-info/METADATA
fixtup-0.1.5.dist-info/WHEEL
fixtup-0.1.5.dist-info/entry_points.txt
fixtup-0.1.5.dist-info/top_level.txt
fixtup-0.1.5.dist-info/RECORD
