Metadata-Version: 2.1
Name: fixtup
Version: 0.1.5
Summary: integration testing on steroids
Home-page: https://github.com/FabienArcellier/fixtup
License: MIT
Project-URL: Documentation, https://fixtup.readthedocs.io/en/latest/index.html
Project-URL: Source, https://github.com/FabienArcellier/fixtup
Classifier: Development Status :: 3 - Alpha
Classifier: Framework :: Pytest
Classifier: Intended Audience :: Developers
Classifier: License :: OSI Approved :: MIT License
Classifier: Operating System :: OS Independent
Classifier: Programming Language :: Python
Classifier: Topic :: Software Development :: Libraries :: Application Frameworks
Classifier: Topic :: Software Development :: Quality Assurance
Classifier: Topic :: Software Development :: Testing
Classifier: Topic :: Software Development :: Testing :: Acceptance
Classifier: Topic :: Software Development :: Testing :: Mocking
Requires-Python: >=3.6
License-File: LICENSE.md
Requires-Dist: attrs
Requires-Dist: click
Requires-Dist: jinja2
Requires-Dist: prompt-toolkit
Requires-Dist: plumbum
Requires-Dist: pyyaml
Requires-Dist: python-dotenv
Requires-Dist: requests
Requires-Dist: toml
Provides-Extra: dev
Requires-Dist: alfred-cli ; extra == 'dev'
Requires-Dist: build ; extra == 'dev'
Requires-Dist: mypy ; extra == 'dev'
Requires-Dist: sphinx ; extra == 'dev'
Requires-Dist: sphinx-rtd-theme ; extra == 'dev'
Requires-Dist: types-requests ; extra == 'dev'
Requires-Dist: types-PyYAML ; extra == 'dev'
Requires-Dist: types-toml ; extra == 'dev'
Requires-Dist: twine ; extra == 'dev'
Provides-Extra: dev_windows
Requires-Dist: alfred-cli ; extra == 'dev_windows'
Requires-Dist: types-PyYAML ; extra == 'dev_windows'
Requires-Dist: types-toml ; extra == 'dev_windows'
